{
    "TOKEN_SALUTATION": {
        "de": {
            "pattern": "(Herrn?|Frau|Fr\\.|Mrs\\.?|Mr\\.?|Ms\\.?|Miss|Mx\\.?)",
            "flags": "i",
            "description": "Deutsche und Englische Anreden (Mixed Data Support)",
            "examples": [
                "Herr",
                "Frau",
                "Mrs.",
                "Mr."
            ],
            "category": "salutation"
        },
        "en": {
            "pattern": "(Mrs\\.?|Mr\\.?|Ms\\.?|Miss|Mx\\.?)",
            "flags": "i",
            "description": "Englische Anreden",
            "examples": [
                "Mrs.",
                "Mr."
            ],
            "category": "salutation"
        },
        "fr": {
            "pattern": "(Monsieur|Madame|Mademoiselle|M\\.|Mme|Mlle)",
            "flags": "i",
            "description": "Französische Anreden",
            "examples": [
                "M.",
                "Mme"
            ],
            "category": "salutation"
        }
    },
    "TOKEN_TITLE": {
        "de": {
            "pattern": "(Dr\\.?|Prof\\.?|Dipl\\.-?Ing\\.?|Dipl\\.-?Kfm\\.?|Mag\\.|med\\.?)",
            "flags": "i",
            "description": "Deutsche Titel",
            "examples": [
                "Dr.",
                "Prof.",
                "med."
            ],
            "category": "title"
        },
        "en": {
            "pattern": "(Dr\\.?|Prof\\.?|Sir|Dame|Lord|Lady)",
            "flags": "i",
            "description": "Englische Titel",
            "examples": [
                "Dr.",
                "Sir"
            ],
            "category": "title"
        },
        "fr": {
            "pattern": "(Dr\\.?|Pr\\.?|Me)",
            "flags": "i",
            "description": "Französische Titel",
            "examples": [
                "Dr.",
                "Me"
            ],
            "category": "title"
        }
    },
    "TOKEN_DEGREE": {
        "de": {
            "pattern": "\\b(B\\.?A\\.?|M\\.?A\\.?|B\\.?Sc\\.?|M\\.?Sc\\.?|Dr\\. h\\.c\\.|PhD)\\b",
            "flags": "i",
            "description": "Akademische Grade (mit Word Boundary)",
            "examples": [
                "B.A.",
                "M.A."
            ],
            "category": "degree"
        },
        "en": {
            "pattern": "\\b(Ph\\.?D\\.?|M\\.?D\\.?|B\\.?A\\.?|M\\.?A\\.?|B\\.?Sc\\.?|M\\.?Sc\\.?|M\\.?B\\.?A\\.?|MBA|Esq\\.?)\\b",
            "flags": "i",
            "description": "Englische Grade",
            "examples": [
                "PhD",
                "MBA"
            ],
            "category": "degree"
        },
        "fr": {
            "pattern": "\\b(Ph\\.?D\\.?|M\\.?D\\.?|Doc\\.)\\b",
            "flags": "i",
            "description": "Französische Grade",
            "examples": [
                "PhD"
            ],
            "category": "degree"
        }
    },
    "TOKEN_INITIAL": {
        "de": {
            "pattern": "[A-ZÄÖÜ]\\.",
            "flags": "",
            "description": "Initiale",
            "examples": [
                "H."
            ],
            "category": "initial"
        },
        "en": {
            "pattern": "[A-Z]\\.",
            "flags": "",
            "description": "Initiale",
            "examples": [
                "J."
            ],
            "category": "initial"
        },
        "fr": {
            "pattern": "[A-ZÀ-ÖØ-Þ]\\.",
            "flags": "",
            "description": "Initiale",
            "examples": [
                "É."
            ],
            "category": "initial"
        }
    },
    "TOKEN_PARTICLE": {
        "de": {
            "pattern": "(von(?: der| dem| den)?|zu(?:r|m)?|auf|aus|am|an|im|in)",
            "flags": "i",
            "description": "Deutsche Partikel",
            "examples": [
                "von"
            ],
            "category": "particle"
        },
        "en": {
            "pattern": "(van(?: der)?|von|de(?: la)?|du|da|del|della|di|dos|st\\.|st)",
            "flags": "i",
            "description": "Englische Partikel",
            "examples": [
                "van"
            ],
            "category": "particle"
        },
        "fr": {
            "pattern": "(de(?: la)?|du|des|d['’]|l['’]|le|la)",
            "flags": "i",
            "description": "Französische Partikel",
            "examples": [
                "de"
            ],
            "category": "particle"
        }
    },
    "TOKEN_SUFFIX": {
        "de": {
            "pattern": "\\b(jun|sen)(\\.?|\\b)",
            "flags": "i",
            "description": "Suffixe (mit Boundary)",
            "examples": [
                "jun."
            ],
            "category": "suffix"
        },
        "en": {
            "pattern": "\\b(Jr|Sr|II|III|IV|V|2nd|3rd)(\\.?|\\b)",
            "flags": "i",
            "description": "Suffixe (mit Boundary)",
            "examples": [
                "Jr."
            ],
            "category": "suffix"
        },
        "fr": {
            "pattern": "\\b(fils|père)\\b",
            "flags": "i",
            "description": "Suffixe (mit Boundary)",
            "examples": [
                "fils"
            ],
            "category": "suffix"
        }
    },
    "TOKEN_WORD": {
        "de": {
            "pattern": "[A-Za-zÄÖÜäöüß]+(?:-[A-Za-zÄÖÜäöüß]+)*",
            "flags": "",
            "description": "Wort",
            "examples": [
                "Müller"
            ],
            "category": "word"
        },
        "en": {
            "pattern": "[A-Za-z]+(?:['’][A-Za-z]+)*(?:-[A-Za-z]+)*",
            "flags": "",
            "description": "Wort",
            "examples": [
                "Smith"
            ],
            "category": "word"
        },
        "fr": {
            "pattern": "[A-Za-zÀ-ÖØ-öø-ÿ]+(?:['’][A-Za-zÀ-ÖØ-öø-ÿ]+)*(?:-[A-Za-zÀ-ÖØ-öø-ÿ]+)*",
            "flags": "",
            "description": "Wort",
            "examples": [
                "François"
            ],
            "category": "word"
        }
    },
    "TOKEN_PUNCT": {
        "de": {
            "pattern": "[,.-]",
            "flags": "",
            "description": "Satzzeichen",
            "examples": [
                "."
            ],
            "category": "punctuation"
        },
        "en": {
            "pattern": "[,.-]",
            "flags": "",
            "description": "Satzzeichen",
            "examples": [
                "."
            ],
            "category": "punctuation"
        },
        "fr": {
            "pattern": "[,.-]",
            "flags": "",
            "description": "Satzzeichen",
            "examples": [
                "."
            ],
            "category": "punctuation"
        }
    }
}